a/__init__.py
a/module.py
b/__init__.py
b/module.py
a9j-2.2.3.dist-info/METADATA
a9j-2.2.3.dist-info/WHEEL
a9j-2.2.3.dist-info/top_level.txt
a9j-2.2.3.dist-info/RECORD
