Metadata-Version: 2.1
Name: a9j
Version: 2.2.3
Summary: noodle contest
Author: luyendd
Author-email: tudu8603@gmail.com
